Metadata-Version: 2.4
Name: topsis-lovepreet-102303335
Version: 0.1.0
Summary: TOPSIS implementation for multi-criteria decision making
Author: Lovepreet Bhatia
Author-email: lovepreetbhatia178@gmail.com
Requires-Python: >=3.7
Requires-Dist: pandas
Requires-Dist: numpy
Dynamic: author
Dynamic: author-email
Dynamic: description
Dynamic: description-content-type
Dynamic: requires-dist
Dynamic: requires-python
Dynamic: summary
